LICENSE
MANIFEST.in
README.md
setup.cfg
setup.py
pydaemo/__init__.py
pydaemo/lib.py
pydaemo/utils.py
pydaemo.egg-info/PKG-INFO
pydaemo.egg-info/SOURCES.txt
pydaemo.egg-info/dependency_links.txt
pydaemo.egg-info/not-zip-safe
pydaemo.egg-info/top_level.txt