Metadata-Version: 1.1
Name: pydaemo
Version: 0.1
Summary: Python wrapper for Daemo: a crowdsourcing platform.
Home-page: http://github.com/ranjaykrishna/pydaemo
Author: Ranjay Krishna
Author-email: ranjaykrishna@gmail.com
License: MIT
Platform: UNKNOWN
Classifier: Development Status :: 3 - Alpha
Classifier: Intended Audience :: Developers
Classifier: Intended Audience :: Education
Classifier: Intended Audience :: Science/Research
Classifier: License :: OSI Approved :: MIT License
Classifier: Programming Language :: Python :: 3
Classifier: Programming Language :: Python :: 3.6
Classifier: Topic :: Software Development :: Libraries
Classifier: Topic :: Software Development :: Libraries :: Python Modules
